{
    "Bass":{
        "C:\\Users\\mysti\\BadIter\\Bass\\Bass_0sGoldnutBass5.wav":true,
        "C:\\Users\\mysti\\BadIter\\Bass\\Bass_10ssBelizeBass6.wav":true,
        "C:\\Users\\mysti\\BadIter\\Bass\\Bass_11assBeninBass1.wav":true,
        "C:\\Users\\mysti\\BadIter\\Bass\\Bass_12ssIslandBass1.wav":true,
        "C:\\Users\\mysti\\BadIter\\Bass\\Bass_13hnoSynthBass1.wav":true,
        "C:\\Users\\mysti\\BadIter\\Bass\\Bass_14BassDeepEyes6.wav":true,
        "C:\\Users\\mysti\\BadIter\\Bass\\Bass_15BassVinylbass1.wav":true,
        "C:\\Users\\mysti\\BadIter\\Bass\\Bass_16ssCowboyBass2.wav":true,
        "C:\\Users\\mysti\\BadIter\\Bass\\Bass_17BassVinylbass5.wav":true,
        "C:\\Users\\mysti\\BadIter\\Bass\\Bass_18ssMysticBass5.wav":true,
        "C:\\Users\\mysti\\BadIter\\Bass\\Bass_19dAgainstBass3.wav":true,
        "C:\\Users\\mysti\\BadIter\\Bass\\Bass_1EchoBassStab6.wav":true,
        "C:\\Users\\mysti\\BadIter\\Bass\\Bass_20sPumpingBass5.wav":true,
        "C:\\Users\\mysti\\BadIter\\Bass\\Bass_21BassDLYHigh6.wav":true,
        "C:\\Users\\mysti\\BadIter\\Bass\\Bass_22EchoBassStab1.wav":true,
        "C:\\Users\\mysti\\BadIter\\Bass\\Bass_23assPowerBass5.wav":true,
        "C:\\Users\\mysti\\BadIter\\Bass\\Bass_24BassResoDrop2.wav":true,
        "C:\\Users\\mysti\\BadIter\\Bass\\Bass_25useOrganBass4.wav":true,
        "C:\\Users\\mysti\\BadIter\\Bass\\Bass_26sNaturalBass1.wav":true,
        "C:\\Users\\mysti\\BadIter\\Bass\\Bass_27sBreathyBass7.wav":true,
        "C:\\Users\\mysti\\BadIter\\Bass\\Bass_28sGoldnutBass4.wav":true,
        "C:\\Users\\mysti\\BadIter\\Bass\\Bass_29BassDeepabass4.wav":true,
        "C:\\Users\\mysti\\BadIter\\Bass\\Bass_2ssPunchyBass6.wav":true,
        "C:\\Users\\mysti\\BadIter\\Bass\\Bass_30DarkAsiaBass4.wav":true,
        "C:\\Users\\mysti\\BadIter\\Bass\\Bass_31dAgainstBass7.wav":true,
        "C:\\Users\\mysti\\BadIter\\Bass\\Bass_32BerlinVerbass5.wav":true,
        "C:\\Users\\mysti\\BadIter\\Bass\\Bass_33ssCowboyBass3.wav":true,
        "C:\\Users\\mysti\\BadIter\\Bass\\Bass_34sGoldnutBass7.wav":true,
        "C:\\Users\\mysti\\BadIter\\Bass\\Bass_35TurnAwayBass6.wav":true,
        "C:\\Users\\mysti\\BadIter\\Bass\\Bass_36ssYoleleBass7.wav":true,
        "C:\\Users\\mysti\\BadIter\\Bass\\Bass_37dioBassSolid7.wav":true,
        "C:\\Users\\mysti\\BadIter\\Bass\\Bass_38ssPunchyBass5.wav":true,
        "C:\\Users\\mysti\\BadIter\\Bass\\Bass_39JungleBassA6.wav":true,
        "C:\\Users\\mysti\\BadIter\\Bass\\Bass_3RadioBassGum5.wav":true,
        "C:\\Users\\mysti\\BadIter\\Bass\\Bass_40ssSummerBass1.wav":true,
        "C:\\Users\\mysti\\BadIter\\Bass\\Bass_41BassSadBass5.wav":true,
        "C:\\Users\\mysti\\BadIter\\Bass\\Bass_42adioBassPump2.wav":true,
        "C:\\Users\\mysti\\BadIter\\Bass\\Bass_43BassLowBass4.wav":true,
        "C:\\Users\\mysti\\BadIter\\Bass\\Bass_44adioBassXoff1.wav":true,
        "C:\\Users\\mysti\\BadIter\\Bass\\Bass_45ssIslandBass1.wav":true,
        "C:\\Users\\mysti\\BadIter\\Bass\\Bass_46BassBendbass5.wav":true,
        "C:\\Users\\mysti\\BadIter\\Bass\\Bass_47Loop23125bpmE.wav":true,
        "C:\\Users\\mysti\\BadIter\\Bass\\Bass_48assPowerBass1.wav":true,
        "C:\\Users\\mysti\\BadIter\\Bass\\Bass_49SwazilandBass7.wav":true,
        "C:\\Users\\mysti\\BadIter\\Bass\\Bass_4assBeninBass5.wav":true,
        "C:\\Users\\mysti\\BadIter\\Bass\\Bass_5BassBeninSub6.wav":true,
        "C:\\Users\\mysti\\BadIter\\Bass\\Bass_6useOrganBass1.wav":true,
        "C:\\Users\\mysti\\BadIter\\Bass\\Bass_7EchoSubBass2.wav":true,
        "C:\\Users\\mysti\\BadIter\\Bass\\Bass_8BassTriabass2.wav":true,
        "C:\\Users\\mysti\\BadIter\\Bass\\Bass_9RadioBassGum3.wav":true
    },
    "Beats":{
        "C:\\Users\\mysti\\BadIter\\Beats\\Beat_0wazilandDrumsB.wav":true,
        "C:\\Users\\mysti\\BadIter\\Beats\\Beat_10msBerlinBeatN.wav":true,
        "C:\\Users\\mysti\\BadIter\\Beats\\Beat_11sYoleleDrumsS.wav":true,
        "C:\\Users\\mysti\\BadIter\\Beats\\Beat_12msBerlinBeatP.wav":true,
        "C:\\Users\\mysti\\BadIter\\Beats\\Beat_13msBeachHouseD.wav":true,
        "C:\\Users\\mysti\\BadIter\\Beats\\Beat_14msBeachHouseL.wav":true,
        "C:\\Users\\mysti\\BadIter\\Beats\\Beat_15sBreathyBeatB.wav":true,
        "C:\\Users\\mysti\\BadIter\\Beats\\Beat_16msMysticBeatC.wav":true,
        "C:\\Users\\mysti\\BadIter\\Beats\\Beat_17eteNoDrumsFx5.wav":true,
        "C:\\Users\\mysti\\BadIter\\Beats\\Beat_18msJungleBeatH.wav":true,
        "C:\\Users\\mysti\\BadIter\\Beats\\Beat_19msBerlinBeatC.wav":true,
        "C:\\Users\\mysti\\BadIter\\Beats\\Beat_1msPunchyBeatL.wav":true,
        "C:\\Users\\mysti\\BadIter\\Beats\\Beat_20dHouseDrumsA1.wav":true,
        "C:\\Users\\mysti\\BadIter\\Beats\\Beat_21dioDrumsToonF.wav":true,
        "C:\\Users\\mysti\\BadIter\\Beats\\Beat_22sVoodooDrumsD.wav":true,
        "C:\\Users\\mysti\\BadIter\\Beats\\Beat_23msJungleBeatB.wav":true,
        "C:\\Users\\mysti\\BadIter\\Beats\\Beat_24dioDrumsFreeA.wav":true,
        "C:\\Users\\mysti\\BadIter\\Beats\\Beat_25umsIronyBeatH.wav":true,
        "C:\\Users\\mysti\\BadIter\\Beats\\Beat_26umsTouchBeatO.wav":true,
        "C:\\Users\\mysti\\BadIter\\Beats\\Beat_27sVoodooDrumsF.wav":true,
        "C:\\Users\\mysti\\BadIter\\Beats\\Beat_28IllusionBeatB.wav":true,
        "C:\\Users\\mysti\\BadIter\\Beats\\Beat_29sBreathyBeatM.wav":true,
        "C:\\Users\\mysti\\BadIter\\Beats\\Beat_2msSummerBeatS.wav":true,
        "C:\\Users\\mysti\\BadIter\\Beats\\Beat_30YoleleDrumFxD.wav":true,
        "C:\\Users\\mysti\\BadIter\\Beats\\Beat_31msBeninDrumsA.wav":true,
        "C:\\Users\\mysti\\BadIter\\Beats\\Beat_32umsPowerBeatF.wav":true,
        "C:\\Users\\mysti\\BadIter\\Beats\\Beat_33eHouseDanceA4.wav":true,
        "C:\\Users\\mysti\\BadIter\\Beats\\Beat_34wazilandDrumsE.wav":true,
        "C:\\Users\\mysti\\BadIter\\Beats\\Beat_35AgainstDrumsD.wav":true,
        "C:\\Users\\mysti\\BadIter\\Beats\\Beat_36sBelizeDrumsC.wav":true,
        "C:\\Users\\mysti\\BadIter\\Beats\\Beat_37msBerlinBeatE.wav":true,
        "C:\\Users\\mysti\\BadIter\\Beats\\Beat_38msBeachHouseD.wav":true,
        "C:\\Users\\mysti\\BadIter\\Beats\\Beat_39sBreathyBeatO.wav":true,
        "C:\\Users\\mysti\\BadIter\\Beats\\Beat_3sIslandDrumsP.wav":true,
        "C:\\Users\\mysti\\BadIter\\Beats\\Beat_40umsTouchBeatV.wav":true,
        "C:\\Users\\mysti\\BadIter\\Beats\\Beat_41sIslandDrumsJ.wav":true,
        "C:\\Users\\mysti\\BadIter\\Beats\\Beat_42YouIDrumsC.wav":true,
        "C:\\Users\\mysti\\BadIter\\Beats\\Beat_43sRollingBeatO.wav":true,
        "C:\\Users\\mysti\\BadIter\\Beats\\Beat_44psHouseBeat22.wav":true,
        "C:\\Users\\mysti\\BadIter\\Beats\\Beat_45BelizeDrumFxC.wav":true,
        "C:\\Users\\mysti\\BadIter\\Beats\\Beat_46msBeachHouseC.wav":true,
        "C:\\Users\\mysti\\BadIter\\Beats\\Beat_47rumsCoolBeatG.wav":true,
        "C:\\Users\\mysti\\BadIter\\Beats\\Beat_48sVoodooDrumsR.wav":true,
        "C:\\Users\\mysti\\BadIter\\Beats\\Beat_49dHouseDrumsA2.wav":true,
        "C:\\Users\\mysti\\BadIter\\Beats\\Beat_4sCowboyDrumsL.wav":true,
        "C:\\Users\\mysti\\BadIter\\Beats\\Beat_50eHouseDanceA3.wav":true,
        "C:\\Users\\mysti\\BadIter\\Beats\\Beat_51rabesqueDrumsA.wav":true,
        "C:\\Users\\mysti\\BadIter\\Beats\\Beat_52sNaturalBeatN.wav":true,
        "C:\\Users\\mysti\\BadIter\\Beats\\Beat_53psHouseBeat08.wav":true,
        "C:\\Users\\mysti\\BadIter\\Beats\\Beat_54msBeninDrumsL.wav":true,
        "C:\\Users\\mysti\\BadIter\\Beats\\Beat_55msSummerBeatJ.wav":true,
        "C:\\Users\\mysti\\BadIter\\Beats\\Beat_56DarkAsiaBeatB.wav":true,
        "C:\\Users\\mysti\\BadIter\\Beats\\Beat_57urnAwayDrumsE.wav":true,
        "C:\\Users\\mysti\\BadIter\\Beats\\Beat_58GoldnutDrumsS.wav":true,
        "C:\\Users\\mysti\\BadIter\\Beats\\Beat_59FabricalDrumsN.wav":true,
        "C:\\Users\\mysti\\BadIter\\Beats\\Beat_5aceEchoDrumsE.wav":true,
        "C:\\Users\\mysti\\BadIter\\Beats\\Beat_60sCowboyDrumsE.wav":true,
        "C:\\Users\\mysti\\BadIter\\Beats\\Beat_61urnAwayDrumsA.wav":true,
        "C:\\Users\\mysti\\BadIter\\Beats\\Beat_62TensionDrumsF.wav":true,
        "C:\\Users\\mysti\\BadIter\\Beats\\Beat_63DarkAsiaBeatN.wav":true,
        "C:\\Users\\mysti\\BadIter\\Beats\\Beat_64sBelizeDrumsK.wav":true,
        "C:\\Users\\mysti\\BadIter\\Beats\\Beat_65sBreathyBeatK.wav":true,
        "C:\\Users\\mysti\\BadIter\\Beats\\Beat_66sRollingBeatB.wav":true,
        "C:\\Users\\mysti\\BadIter\\Beats\\Beat_67sRollingBeatA.wav":true,
        "C:\\Users\\mysti\\BadIter\\Beats\\Beat_68sYoleleDrumsS.wav":true,
        "C:\\Users\\mysti\\BadIter\\Beats\\Beat_69dioDrumsFreeD.wav":true,
        "C:\\Users\\mysti\\BadIter\\Beats\\Beat_6msBerlinBeatE.wav":true,
        "C:\\Users\\mysti\\BadIter\\Beats\\Beat_70umsTouchBeatO.wav":true,
        "C:\\Users\\mysti\\BadIter\\Beats\\Beat_71urnAwayDrumsF.wav":true,
        "C:\\Users\\mysti\\BadIter\\Beats\\Beat_72rabesqueDrumsE.wav":true,
        "C:\\Users\\mysti\\BadIter\\Beats\\Beat_73msSummerBeatS.wav":true,
        "C:\\Users\\mysti\\BadIter\\Beats\\Beat_74sNaturalBeatK.wav":true,
        "C:\\Users\\mysti\\BadIter\\Beats\\Beat_75GoldnutDrumsU.wav":true,
        "C:\\Users\\mysti\\BadIter\\Beats\\Beat_76rumsGlasHouseB.wav":true,
        "C:\\Users\\mysti\\BadIter\\Beats\\Beat_77AgainstDrumsB.wav":true,
        "C:\\Users\\mysti\\BadIter\\Beats\\Beat_78BelizeDrumFxE.wav":true,
        "C:\\Users\\mysti\\BadIter\\Beats\\Beat_79rabesqueDrumsB.wav":true,
        "C:\\Users\\mysti\\BadIter\\Beats\\Beat_7msSummerBeatE.wav":true,
        "C:\\Users\\mysti\\BadIter\\Beats\\Beat_8dioDrumsEasyD.wav":true,
        "C:\\Users\\mysti\\BadIter\\Beats\\Beat_9IllusionBeatI.wav":true
    },
    "Drone":{
        "C:\\Users\\mysti\\BadIter\\Drone\\Drone_0VoodooClacker3.wav":true,
        "C:\\Users\\mysti\\BadIter\\Drone\\Drone_10SequenceFlow1.wav":true,
        "C:\\Users\\mysti\\BadIter\\Drone\\Drone_11nceIslandArp2.wav":true,
        "C:\\Users\\mysti\\BadIter\\Drone\\Drone_12owboyOffSynth1.wav":true,
        "C:\\Users\\mysti\\BadIter\\Drone\\Drone_13eleOrganesque3.wav":true,
        "C:\\Users\\mysti\\BadIter\\Drone\\Drone_14SequenceBower1.wav":true,
        "C:\\Users\\mysti\\BadIter\\Drone\\Drone_15boySequenceB2.wav":true,
        "C:\\Users\\mysti\\BadIter\\Drone\\Drone_16eBreathyCall7.wav":true,
        "C:\\Users\\mysti\\BadIter\\Drone\\Drone_17IronySequence3.wav":true,
        "C:\\Users\\mysti\\BadIter\\Drone\\Drone_18AwaySynthArp3.wav":true,
        "C:\\Users\\mysti\\BadIter\\Drone\\Drone_19AwaySynthSeq4.wav":true,
        "C:\\Users\\mysti\\BadIter\\Drone\\Drone_1ceIslandArpy1.wav":true,
        "C:\\Users\\mysti\\BadIter\\Drone\\Drone_20erlinSequence7.wav":true,
        "C:\\Users\\mysti\\BadIter\\Drone\\Drone_21usionSequence3.wav":true,
        "C:\\Users\\mysti\\BadIter\\Drone\\Drone_22quenceTekSeq5.wav":true,
        "C:\\Users\\mysti\\BadIter\\Drone\\Drone_23CowboyBleeper7.wav":true,
        "C:\\Users\\mysti\\BadIter\\Drone\\Drone_24SummerBreeze4.wav":true,
        "C:\\Users\\mysti\\BadIter\\Drone\\Drone_25quenceTekSeq4.wav":true,
        "C:\\Users\\mysti\\BadIter\\Drone\\Drone_26nceIslandArp2.wav":true,
        "C:\\Users\\mysti\\BadIter\\Drone\\Drone_27JungleBleeps3.wav":true,
        "C:\\Users\\mysti\\BadIter\\Drone\\Drone_28SequenceFlow6.wav":true,
        "C:\\Users\\mysti\\BadIter\\Drone\\Drone_29erlinSequence3.wav":true,
        "C:\\Users\\mysti\\BadIter\\Drone\\Drone_2ncePluckVille1.wav":true,
        "C:\\Users\\mysti\\BadIter\\Drone\\Drone_30nceCoolRythm3.wav":true,
        "C:\\Users\\mysti\\BadIter\\Drone\\Drone_31ceNaturalArp2.wav":true,
        "C:\\Users\\mysti\\BadIter\\Drone\\Drone_32abesqueHiSeq7.wav":true,
        "C:\\Users\\mysti\\BadIter\\Drone\\Drone_33nceIslandArp4.wav":true,
        "C:\\Users\\mysti\\BadIter\\Drone\\Drone_34ceAlphaChord4.wav":true,
        "C:\\Users\\mysti\\BadIter\\Drone\\Drone_35ooClackerAdd6.wav":true,
        "C:\\Users\\mysti\\BadIter\\Drone\\Drone_36slandSequence2.wav":true,
        "C:\\Users\\mysti\\BadIter\\Drone\\Drone_37eMysticPluck7.wav":true,
        "C:\\Users\\mysti\\BadIter\\Drone\\Drone_38equenceVector1.wav":true,
        "C:\\Users\\mysti\\BadIter\\Drone\\Drone_39ceGhostStory5.wav":true,
        "C:\\Users\\mysti\\BadIter\\Drone\\Drone_3AwaySynthSeq2.wav":true,
        "C:\\Users\\mysti\\BadIter\\Drone\\Drone_40ceNaturalArp5.wav":true,
        "C:\\Users\\mysti\\BadIter\\Drone\\Drone_41nceTekGuitar6.wav":true,
        "C:\\Users\\mysti\\BadIter\\Drone\\Drone_42quenceTekSeq4.wav":true,
        "C:\\Users\\mysti\\BadIter\\Drone\\Drone_43AwaySynthSeq4.wav":true,
        "C:\\Users\\mysti\\BadIter\\Drone\\Drone_44IronySequence1.wav":true,
        "C:\\Users\\mysti\\BadIter\\Drone\\Drone_45SequenceBower4.wav":true,
        "C:\\Users\\mysti\\BadIter\\Drone\\Drone_46ceIslandArpy1.wav":true,
        "C:\\Users\\mysti\\BadIter\\Drone\\Drone_47SequenceBower3.wav":true,
        "C:\\Users\\mysti\\BadIter\\Drone\\Drone_48eMutedHiSeq3.wav":true,
        "C:\\Users\\mysti\\BadIter\\Drone\\Drone_49ceIslandArpy2.wav":true,
        "C:\\Users\\mysti\\BadIter\\Drone\\Drone_4nceIslandArp6.wav":true,
        "C:\\Users\\mysti\\BadIter\\Drone\\Drone_50quenceTekSeq3.wav":true,
        "C:\\Users\\mysti\\BadIter\\Drone\\Drone_51erlinSequence7.wav":true,
        "C:\\Users\\mysti\\BadIter\\Drone\\Drone_52ceNaturalArp3.wav":true,
        "C:\\Users\\mysti\\BadIter\\Drone\\Drone_53dnutPlugdelay6.wav":true,
        "C:\\Users\\mysti\\BadIter\\Drone\\Drone_54ncePluckVille2.wav":true,
        "C:\\Users\\mysti\\BadIter\\Drone\\Drone_55CowboyBleeper2.wav":true,
        "C:\\Users\\mysti\\BadIter\\Drone\\Drone_56BreathyGroove1.wav":true,
        "C:\\Users\\mysti\\BadIter\\Drone\\Drone_57IronySequence2.wav":true,
        "C:\\Users\\mysti\\BadIter\\Drone\\Drone_58AwaySynthArp7.wav":true,
        "C:\\Users\\mysti\\BadIter\\Drone\\Drone_59eBerlinPluck1.wav":true,
        "C:\\Users\\mysti\\BadIter\\Drone\\Drone_5SummerBreeze2.wav":true,
        "C:\\Users\\mysti\\BadIter\\Drone\\Drone_6ceTekOffbeat1.wav":true,
        "C:\\Users\\mysti\\BadIter\\Drone\\Drone_7ceNaturalArp2.wav":true,
        "C:\\Users\\mysti\\BadIter\\Drone\\Drone_8AwaySynthSeq3.wav":true,
        "C:\\Users\\mysti\\BadIter\\Drone\\Drone_9eleOrganesque6.wav":true
    },
    "Guitar":{
        "C:\\Users\\mysti\\BadIter\\Guitar\\Guitar_0AmbientBeat10.wav":true,
        "C:\\Users\\mysti\\BadIter\\Guitar\\Guitar_10entLandscape01.wav":true,
        "C:\\Users\\mysti\\BadIter\\Guitar\\Guitar_11entLandscape08.wav":true,
        "C:\\Users\\mysti\\BadIter\\Guitar\\Guitar_12AmbientBeat10.wav":true,
        "C:\\Users\\mysti\\BadIter\\Guitar\\Guitar_13entLandscape02.wav":true,
        "C:\\Users\\mysti\\BadIter\\Guitar\\Guitar_14entLandscape09.wav":true,
        "C:\\Users\\mysti\\BadIter\\Guitar\\Guitar_15entLandscape06.wav":true,
        "C:\\Users\\mysti\\BadIter\\Guitar\\Guitar_16AmbientBeat03.wav":true,
        "C:\\Users\\mysti\\BadIter\\Guitar\\Guitar_17AmbientBeat05.wav":true,
        "C:\\Users\\mysti\\BadIter\\Guitar\\Guitar_18AmbientMonks01.wav":true,
        "C:\\Users\\mysti\\BadIter\\Guitar\\Guitar_19sAmbientDrones.wav":true,
        "C:\\Users\\mysti\\BadIter\\Guitar\\Guitar_1AmbientPiano02.wav":true,
        "C:\\Users\\mysti\\BadIter\\Guitar\\Guitar_20AmbientBeat06.wav":true,
        "C:\\Users\\mysti\\BadIter\\Guitar\\Guitar_21ntAtmosphere01.wav":true,
        "C:\\Users\\mysti\\BadIter\\Guitar\\Guitar_22entLandscape05.wav":true,
        "C:\\Users\\mysti\\BadIter\\Guitar\\Guitar_23mbientStrats04.wav":true,
        "C:\\Users\\mysti\\BadIter\\Guitar\\Guitar_24sAmbientDrones.wav":true,
        "C:\\Users\\mysti\\BadIter\\Guitar\\Guitar_25entLandscape07.wav":true,
        "C:\\Users\\mysti\\BadIter\\Guitar\\Guitar_26AmbientBeat13.wav":true,
        "C:\\Users\\mysti\\BadIter\\Guitar\\Guitar_27esAmbientRains.wav":true,
        "C:\\Users\\mysti\\BadIter\\Guitar\\Guitar_28alAmbientVoice.wav":true,
        "C:\\Users\\mysti\\BadIter\\Guitar\\Guitar_29esAmbientRains.wav":true,
        "C:\\Users\\mysti\\BadIter\\Guitar\\Guitar_2mbientNoises03.wav":true,
        "C:\\Users\\mysti\\BadIter\\Guitar\\Guitar_30AmbientBeat14.wav":true,
        "C:\\Users\\mysti\\BadIter\\Guitar\\Guitar_31AmbientMonks01.wav":true,
        "C:\\Users\\mysti\\BadIter\\Guitar\\Guitar_32mbientNoises01.wav":true,
        "C:\\Users\\mysti\\BadIter\\Guitar\\Guitar_33entLandscape03.wav":true,
        "C:\\Users\\mysti\\BadIter\\Guitar\\Guitar_34entLandscape07.wav":true,
        "C:\\Users\\mysti\\BadIter\\Guitar\\Guitar_35mbientStrats04.wav":true,
        "C:\\Users\\mysti\\BadIter\\Guitar\\Guitar_36sAmbientDrones.wav":true,
        "C:\\Users\\mysti\\BadIter\\Guitar\\Guitar_37entLandscape01.wav":true,
        "C:\\Users\\mysti\\BadIter\\Guitar\\Guitar_38AmbientPiano02.wav":true,
        "C:\\Users\\mysti\\BadIter\\Guitar\\Guitar_39AmbientMonks02.wav":true,
        "C:\\Users\\mysti\\BadIter\\Guitar\\Guitar_3mbientStrats05.wav":true,
        "C:\\Users\\mysti\\BadIter\\Guitar\\Guitar_40AmbientBeat03.wav":true,
        "C:\\Users\\mysti\\BadIter\\Guitar\\Guitar_41AmbientBeat03.wav":true,
        "C:\\Users\\mysti\\BadIter\\Guitar\\Guitar_42entLandscape08.wav":true,
        "C:\\Users\\mysti\\BadIter\\Guitar\\Guitar_43AmbientBeat06.wav":true,
        "C:\\Users\\mysti\\BadIter\\Guitar\\Guitar_44mbientStrats05.wav":true,
        "C:\\Users\\mysti\\BadIter\\Guitar\\Guitar_45ntAtmosphere02.wav":true,
        "C:\\Users\\mysti\\BadIter\\Guitar\\Guitar_46ntAtmosphere02.wav":true,
        "C:\\Users\\mysti\\BadIter\\Guitar\\Guitar_47AmbientBeat09.wav":true,
        "C:\\Users\\mysti\\BadIter\\Guitar\\Guitar_48AmbientBeat11.wav":true,
        "C:\\Users\\mysti\\BadIter\\Guitar\\Guitar_49entLandscape05.wav":true,
        "C:\\Users\\mysti\\BadIter\\Guitar\\Guitar_4mbientStrats02.wav":true,
        "C:\\Users\\mysti\\BadIter\\Guitar\\Guitar_5esAmbientRains.wav":true,
        "C:\\Users\\mysti\\BadIter\\Guitar\\Guitar_6AmbientBeat05.wav":true,
        "C:\\Users\\mysti\\BadIter\\Guitar\\Guitar_7entLandscape08.wav":true,
        "C:\\Users\\mysti\\BadIter\\Guitar\\Guitar_8AmbientBeat05.wav":true,
        "C:\\Users\\mysti\\BadIter\\Guitar\\Guitar_9mbientStrats03.wav":true
    },
    "Organ":{
        "C:\\Users\\mysti\\BadIter\\Organ\\Organ0HitsDSPHit16.wav":true,
        "C:\\Users\\mysti\\BadIter\\Organ\\Organ10HitsDSPHit03.wav":true,
        "C:\\Users\\mysti\\BadIter\\Organ\\Organ11HitsDSPHit05.wav":true,
        "C:\\Users\\mysti\\BadIter\\Organ\\Organ12HitsDSPHit06.wav":true,
        "C:\\Users\\mysti\\BadIter\\Organ\\Organ13HitsDSPHit14.wav":true,
        "C:\\Users\\mysti\\BadIter\\Organ\\Organ14HitsDSPHit14.wav":true,
        "C:\\Users\\mysti\\BadIter\\Organ\\Organ15HitsDSPHit16.wav":true,
        "C:\\Users\\mysti\\BadIter\\Organ\\Organ16HitsDSPHit13.wav":true,
        "C:\\Users\\mysti\\BadIter\\Organ\\Organ17HitsDSPHit13.wav":true,
        "C:\\Users\\mysti\\BadIter\\Organ\\Organ18HitsDSPHit21.wav":true,
        "C:\\Users\\mysti\\BadIter\\Organ\\Organ19HitsDSPHit04.wav":true,
        "C:\\Users\\mysti\\BadIter\\Organ\\Organ1HitsDSPHit19.wav":true,
        "C:\\Users\\mysti\\BadIter\\Organ\\Organ20HitsDSPHit01.wav":true,
        "C:\\Users\\mysti\\BadIter\\Organ\\Organ21HitsDSPHit06.wav":true,
        "C:\\Users\\mysti\\BadIter\\Organ\\Organ22HitsDSPHit10.wav":true,
        "C:\\Users\\mysti\\BadIter\\Organ\\Organ23HitsDSPHit10.wav":true,
        "C:\\Users\\mysti\\BadIter\\Organ\\Organ24HitsDSPHit23.wav":true,
        "C:\\Users\\mysti\\BadIter\\Organ\\Organ25HitsDSPHit08.wav":true,
        "C:\\Users\\mysti\\BadIter\\Organ\\Organ26HitsDSPHit16.wav":true,
        "C:\\Users\\mysti\\BadIter\\Organ\\Organ27HitsDSPHit09.wav":true,
        "C:\\Users\\mysti\\BadIter\\Organ\\Organ28HitsDSPHit07.wav":true,
        "C:\\Users\\mysti\\BadIter\\Organ\\Organ29HitsDSPHit04.wav":true,
        "C:\\Users\\mysti\\BadIter\\Organ\\Organ2HitsDSPHit10.wav":true,
        "C:\\Users\\mysti\\BadIter\\Organ\\Organ30HitsDSPHit05.wav":true,
        "C:\\Users\\mysti\\BadIter\\Organ\\Organ31HitsDSPHit20.wav":true,
        "C:\\Users\\mysti\\BadIter\\Organ\\Organ32HitsDSPHit14.wav":true,
        "C:\\Users\\mysti\\BadIter\\Organ\\Organ33HitsDSPHit07.wav":true,
        "C:\\Users\\mysti\\BadIter\\Organ\\Organ34HitsDSPHit09.wav":true,
        "C:\\Users\\mysti\\BadIter\\Organ\\Organ35HitsDSPHit21.wav":true,
        "C:\\Users\\mysti\\BadIter\\Organ\\Organ36HitsDSPHit16.wav":true,
        "C:\\Users\\mysti\\BadIter\\Organ\\Organ37HitsDSPHit19.wav":true,
        "C:\\Users\\mysti\\BadIter\\Organ\\Organ38HitsDSPHit15.wav":true,
        "C:\\Users\\mysti\\BadIter\\Organ\\Organ39HitsDSPHit01.wav":true,
        "C:\\Users\\mysti\\BadIter\\Organ\\Organ3HitsDSPHit16.wav":true,
        "C:\\Users\\mysti\\BadIter\\Organ\\Organ40HitsDSPHit05.wav":true,
        "C:\\Users\\mysti\\BadIter\\Organ\\Organ41HitsDSPHit11.wav":true,
        "C:\\Users\\mysti\\BadIter\\Organ\\Organ42HitsDSPHit15.wav":true,
        "C:\\Users\\mysti\\BadIter\\Organ\\Organ43HitsDSPHit11.wav":true,
        "C:\\Users\\mysti\\BadIter\\Organ\\Organ44HitsDSPHit23.wav":true,
        "C:\\Users\\mysti\\BadIter\\Organ\\Organ45HitsDSPHit22.wav":true,
        "C:\\Users\\mysti\\BadIter\\Organ\\Organ46HitsDSPHit19.wav":true,
        "C:\\Users\\mysti\\BadIter\\Organ\\Organ47HitsDSPHit17.wav":true,
        "C:\\Users\\mysti\\BadIter\\Organ\\Organ48HitsDSPHit16.wav":true,
        "C:\\Users\\mysti\\BadIter\\Organ\\Organ49HitsDSPHit13.wav":true,
        "C:\\Users\\mysti\\BadIter\\Organ\\Organ4HitsDSPHit07.wav":true,
        "C:\\Users\\mysti\\BadIter\\Organ\\Organ5HitsDSPHit19.wav":true,
        "C:\\Users\\mysti\\BadIter\\Organ\\Organ6HitsDSPHit14.wav":true,
        "C:\\Users\\mysti\\BadIter\\Organ\\Organ7HitsDSPHit11.wav":true,
        "C:\\Users\\mysti\\BadIter\\Organ\\Organ8HitsDSPHit01.wav":true,
        "C:\\Users\\mysti\\BadIter\\Organ\\Organ9HitsDSPHit08.wav":true
    },
    "Pepper":{
        "C:\\Users\\mysti\\BadIter\\Pepper\\Pepper_0eatTwinkleLoop.wav":true,
        "C:\\Users\\mysti\\BadIter\\Pepper\\Pepper_10heIlluminati04.wav":true,
        "C:\\Users\\mysti\\BadIter\\Pepper\\Pepper_11RollingRodLoop.wav":true,
        "C:\\Users\\mysti\\BadIter\\Pepper\\Pepper_12ctShellLoop01.wav":true,
        "C:\\Users\\mysti\\BadIter\\Pepper\\Pepper_13nkleLoopperc.wav":true,
        "C:\\Users\\mysti\\BadIter\\Pepper\\Pepper_14ribalGlassLoop.wav":true,
        "C:\\Users\\mysti\\BadIter\\Pepper\\Pepper_15leShellLoop02.wav":true,
        "C:\\Users\\mysti\\BadIter\\Pepper\\Pepper_16moryCrackles01.wav":true,
        "C:\\Users\\mysti\\BadIter\\Pepper\\Pepper_17eatTwinkleLoop.wav":true,
        "C:\\Users\\mysti\\BadIter\\Pepper\\Pepper_18andLollipops01.wav":true,
        "C:\\Users\\mysti\\BadIter\\Pepper\\Pepper_19heIlluminati01.wav":true,
        "C:\\Users\\mysti\\BadIter\\Pepper\\Pepper_1ittleBunnies07.wav":true,
        "C:\\Users\\mysti\\BadIter\\Pepper\\Pepper_20heIlluminati03.wav":true,
        "C:\\Users\\mysti\\BadIter\\Pepper\\Pepper_21nkleLoopperc.wav":true,
        "C:\\Users\\mysti\\BadIter\\Pepper\\Pepper_22micTwinkleLoop.wav":true,
        "C:\\Users\\mysti\\BadIter\\Pepper\\Pepper_23inkleChimeLoop.wav":true,
        "C:\\Users\\mysti\\BadIter\\Pepper\\Pepper_24PrettyRodLoop.wav":true,
        "C:\\Users\\mysti\\BadIter\\Pepper\\Pepper_25ittleBunnies01.wav":true,
        "C:\\Users\\mysti\\BadIter\\Pepper\\Pepper_26tractGlassLoop.wav":true,
        "C:\\Users\\mysti\\BadIter\\Pepper\\Pepper_27ittleBunnies03.wav":true,
        "C:\\Users\\mysti\\BadIter\\Pepper\\Pepper_28PrettyRodLoop.wav":true,
        "C:\\Users\\mysti\\BadIter\\Pepper\\Pepper_29heIlluminati02.wav":true,
        "C:\\Users\\mysti\\BadIter\\Pepper\\Pepper_2actTwinkleLoop.wav":true,
        "C:\\Users\\mysti\\BadIter\\Pepper\\Pepper_30untingBellLoop.wav":true,
        "C:\\Users\\mysti\\BadIter\\Pepper\\Pepper_31GnarledTwinkles.wav":true,
        "C:\\Users\\mysti\\BadIter\\Pepper\\Pepper_32esFastPodLoop.wav":true,
        "C:\\Users\\mysti\\BadIter\\Pepper\\Pepper_33ickShellRythym.wav":true,
        "C:\\Users\\mysti\\BadIter\\Pepper\\Pepper_34moryCrackles02.wav":true,
        "C:\\Users\\mysti\\BadIter\\Pepper\\Pepper_35heIlluminati03.wav":true,
        "C:\\Users\\mysti\\BadIter\\Pepper\\Pepper_36ctShellLoop03.wav":true,
        "C:\\Users\\mysti\\BadIter\\Pepper\\Pepper_37astBellLoop01.wav":true,
        "C:\\Users\\mysti\\BadIter\\Pepper\\Pepper_38kleLoopsnare.wav":true,
        "C:\\Users\\mysti\\BadIter\\Pepper\\Pepper_39sCoolRodLoop.wav":true,
        "C:\\Users\\mysti\\BadIter\\Pepper\\Pepper_3uncingRodLoop.wav":true,
        "C:\\Users\\mysti\\BadIter\\Pepper\\Pepper_40andLollipops03.wav":true,
        "C:\\Users\\mysti\\BadIter\\Pepper\\Pepper_41ittleBunnies08.wav":true,
        "C:\\Users\\mysti\\BadIter\\Pepper\\Pepper_42nkleLoopperc.wav":true,
        "C:\\Users\\mysti\\BadIter\\Pepper\\Pepper_43ittleBunnies11.wav":true,
        "C:\\Users\\mysti\\BadIter\\Pepper\\Pepper_44ittleBunnies08.wav":true,
        "C:\\Users\\mysti\\BadIter\\Pepper\\Pepper_45astBellLoop01.wav":true,
        "C:\\Users\\mysti\\BadIter\\Pepper\\Pepper_46ittleBunnies06.wav":true,
        "C:\\Users\\mysti\\BadIter\\Pepper\\Pepper_47nkleLoopperc.wav":true,
        "C:\\Users\\mysti\\BadIter\\Pepper\\Pepper_48ctShellLoop02.wav":true,
        "C:\\Users\\mysti\\BadIter\\Pepper\\Pepper_49inkleChimeLoop.wav":true,
        "C:\\Users\\mysti\\BadIter\\Pepper\\Pepper_4rackleRodLoop.wav":true,
        "C:\\Users\\mysti\\BadIter\\Pepper\\Pepper_50ittleBunnies08.wav":true,
        "C:\\Users\\mysti\\BadIter\\Pepper\\Pepper_51ractPodLoop02.wav":true,
        "C:\\Users\\mysti\\BadIter\\Pepper\\Pepper_52PrettyRodLoop.wav":true,
        "C:\\Users\\mysti\\BadIter\\Pepper\\Pepper_532500STTwinkles.wav":true,
        "C:\\Users\\mysti\\BadIter\\Pepper\\Pepper_54ittleBunnies03.wav":true,
        "C:\\Users\\mysti\\BadIter\\Pepper\\Pepper_55GnarledTwinkles.wav":true,
        "C:\\Users\\mysti\\BadIter\\Pepper\\Pepper_56esFastPodLoop.wav":true,
        "C:\\Users\\mysti\\BadIter\\Pepper\\Pepper_57untingBellLoop.wav":true,
        "C:\\Users\\mysti\\BadIter\\Pepper\\Pepper_58bstractKeyLoop.wav":true,
        "C:\\Users\\mysti\\BadIter\\Pepper\\Pepper_59PrettyRodLoop.wav":true,
        "C:\\Users\\mysti\\BadIter\\Pepper\\Pepper_5ribalGlassLoop.wav":true,
        "C:\\Users\\mysti\\BadIter\\Pepper\\Pepper_6eRythmKeyLoop.wav":true,
        "C:\\Users\\mysti\\BadIter\\Pepper\\Pepper_7actTwinkleLoop.wav":true,
        "C:\\Users\\mysti\\BadIter\\Pepper\\Pepper_8nkleLoopperc.wav":true,
        "C:\\Users\\mysti\\BadIter\\Pepper\\Pepper_9andLollipops01.wav":true
    },
    "Saxophone":{
        "C:\\Users\\mysti\\BadIter\\Saxophone\\Saxophone_0OfFxNoiseFxI.wav":true,
        "C:\\Users\\mysti\\BadIter\\Saxophone\\Saxophone_10FxDeadSpeaker5.wav":true,
        "C:\\Users\\mysti\\BadIter\\Saxophone\\Saxophone_11OfFxBeepFreak.wav":true,
        "C:\\Users\\mysti\\BadIter\\Saxophone\\Saxophone_12FxDeadSpeaker1.wav":true,
        "C:\\Users\\mysti\\BadIter\\Saxophone\\Saxophone_13FxDeadSpeaker7.wav":true,
        "C:\\Users\\mysti\\BadIter\\Saxophone\\Saxophone_14OfFxKaputnik1.wav":true,
        "C:\\Users\\mysti\\BadIter\\Saxophone\\Saxophone_15fFxScreaming7.wav":true,
        "C:\\Users\\mysti\\BadIter\\Saxophone\\Saxophone_16OfFxNoiseFxI.wav":true,
        "C:\\Users\\mysti\\BadIter\\Saxophone\\Saxophone_17tOfFxFreakOut.wav":true,
        "C:\\Users\\mysti\\BadIter\\Saxophone\\Saxophone_18fFxScreaming7.wav":true,
        "C:\\Users\\mysti\\BadIter\\Saxophone\\Saxophone_19FxDeadSpeaker1.wav":true,
        "C:\\Users\\mysti\\BadIter\\Saxophone\\Saxophone_1FxGatesofHellB.wav":true,
        "C:\\Users\\mysti\\BadIter\\Saxophone\\Saxophone_20fFxScreaming1.wav":true,
        "C:\\Users\\mysti\\BadIter\\Saxophone\\Saxophone_21OfFxKaputnik7.wav":true,
        "C:\\Users\\mysti\\BadIter\\Saxophone\\Saxophone_22OfFxBeepFreak.wav":true,
        "C:\\Users\\mysti\\BadIter\\Saxophone\\Saxophone_23FxDeadSpeaker4.wav":true,
        "C:\\Users\\mysti\\BadIter\\Saxophone\\Saxophone_24FxSickSqueekB.wav":true,
        "C:\\Users\\mysti\\BadIter\\Saxophone\\Saxophone_25OfFxKaputnik7.wav":true,
        "C:\\Users\\mysti\\BadIter\\Saxophone\\Saxophone_26FxDeadSpeaker5.wav":true,
        "C:\\Users\\mysti\\BadIter\\Saxophone\\Saxophone_27FxGatesofHellA.wav":true,
        "C:\\Users\\mysti\\BadIter\\Saxophone\\Saxophone_28xStrangeSweepD.wav":true,
        "C:\\Users\\mysti\\BadIter\\Saxophone\\Saxophone_29FxDeadSpeaker3.wav":true,
        "C:\\Users\\mysti\\BadIter\\Saxophone\\Saxophone_2FxGatesofHellB.wav":true,
        "C:\\Users\\mysti\\BadIter\\Saxophone\\Saxophone_30FxGatesofHellB.wav":true,
        "C:\\Users\\mysti\\BadIter\\Saxophone\\Saxophone_31OfFxBeepFreak.wav":true,
        "C:\\Users\\mysti\\BadIter\\Saxophone\\Saxophone_32OfFxBreakFxA.wav":true,
        "C:\\Users\\mysti\\BadIter\\Saxophone\\Saxophone_33OfFxBreakFxB.wav":true,
        "C:\\Users\\mysti\\BadIter\\Saxophone\\Saxophone_34FxGatesofHellD.wav":true,
        "C:\\Users\\mysti\\BadIter\\Saxophone\\Saxophone_35xStrangeSweepD.wav":true,
        "C:\\Users\\mysti\\BadIter\\Saxophone\\Saxophone_36OfFxElectroCat.wav":true,
        "C:\\Users\\mysti\\BadIter\\Saxophone\\Saxophone_37fFxScreaming3.wav":true,
        "C:\\Users\\mysti\\BadIter\\Saxophone\\Saxophone_38OfFxBreakFxC.wav":true,
        "C:\\Users\\mysti\\BadIter\\Saxophone\\Saxophone_39FxSickSqueekA.wav":true,
        "C:\\Users\\mysti\\BadIter\\Saxophone\\Saxophone_3fFxScreaming6.wav":true,
        "C:\\Users\\mysti\\BadIter\\Saxophone\\Saxophone_40FxGatesofHellD.wav":true,
        "C:\\Users\\mysti\\BadIter\\Saxophone\\Saxophone_41FxDeadSpeaker1.wav":true,
        "C:\\Users\\mysti\\BadIter\\Saxophone\\Saxophone_42FxDeadSpeaker5.wav":true,
        "C:\\Users\\mysti\\BadIter\\Saxophone\\Saxophone_43OfFxKaputnik1.wav":true,
        "C:\\Users\\mysti\\BadIter\\Saxophone\\Saxophone_44OfFxElectroCat.wav":true,
        "C:\\Users\\mysti\\BadIter\\Saxophone\\Saxophone_45OfFxNoiseFxI.wav":true,
        "C:\\Users\\mysti\\BadIter\\Saxophone\\Saxophone_46FxDeadSpeaker3.wav":true,
        "C:\\Users\\mysti\\BadIter\\Saxophone\\Saxophone_47OfFxSweepFXG.wav":true,
        "C:\\Users\\mysti\\BadIter\\Saxophone\\Saxophone_48FxGatesofHellD.wav":true,
        "C:\\Users\\mysti\\BadIter\\Saxophone\\Saxophone_49OfFxBreakFxD.wav":true,
        "C:\\Users\\mysti\\BadIter\\Saxophone\\Saxophone_4xStrangeSweepD.wav":true,
        "C:\\Users\\mysti\\BadIter\\Saxophone\\Saxophone_5OfFxSweepFXH.wav":true,
        "C:\\Users\\mysti\\BadIter\\Saxophone\\Saxophone_6FxDeadSpeaker4.wav":true,
        "C:\\Users\\mysti\\BadIter\\Saxophone\\Saxophone_7BestOfFxScrew.wav":true,
        "C:\\Users\\mysti\\BadIter\\Saxophone\\Saxophone_8OfFxBreakFxD.wav":true,
        "C:\\Users\\mysti\\BadIter\\Saxophone\\Saxophone_9FxSickSqueekA.wav":true
    }
}